[
  {
    "exportName": "SOCAT",
    "separator": "tab",
    "headerMode": "code",
    "includeCalculationColumns": true,
    "includeUnits": false,
    "timestampHeader": "date time [ yyyy-mm-dd hh:mm:ss ]",
    "replaceColumnHeaders": {
      "ALATGP01": "latitude [ deg N ]",
      "ALONGP01": "longitude [ deg E ]",
      "PSALPR01": "Salinity [ PSU ]",
      "TEMPPR01": "SST [ deg C ]",
      "ACO2XXXX": "pCO2_atm_wet_actual [ uatm ]",
      "FCO2WTAT": "fCO2_atm_wet_actual [ uatm ]",
      "TEMPEQMN": "T_equ [ deg C ]",
      "WMXRZZ01": "xH2O_equi [ umol/mol ]",
      "XCO2DECQ": "xCO2_water_Tequ_dry [ umol/mol ]",
      "PCO2IG02": "pCO2_water_Tequ_wet [ uatm ]",
      "FCO2IG02": "fCO2_water_Tequ_wet [ uatm ]",
      "PCO2TK02": "pCO2_water_SST_wet [ uatm ]",
      "FCO2XXXX": "fCO2_water_SST_wet [ uatm ]",
      "CAPAZZ01": "P_atm [ hPa ]",
      "XCO2DCMA": "xCO2_atm_dry_actual [ umol/mol ]",
      "ADEPZZ01": "Depth [ m ]"
    }
  },
  {
    "exportName": "ICOS OTC",
    "separator": "comma",
    "headerMode": "short",
    "includeCalculationColumns": false,
    "includeUnits": false,
    "timestampHeader": "Date/Time",
    "replaceColumnHeaders": {
      "ALATGP01": "Latitude",
      "ALONGP01": "Longitude",
      "PSALPR01": "P_sal [psu]",
      "TEMPPR01": "Temp [degC]",
      "FCO2XXXX": "fCO2 [uatm]",
      "PCO2TK02": "pCO2 [uatm]",
      "ACO2XXXX": "pCO2 in atmosphere [uatm]",
      "FCO2WTAT": "fCO2 in atmosphere [uatm]",
      "ADEPZZ01": "Depth [m]",
      "CAPHZZ01": "Atmospheric Pressure [hPa]",
      "PRESAMB": "Instrument Ambient Pressure [hPa]",
      "XCO2EQWT": "CO2 Mole Fraction [umol mol-1]",
      "TEMPEQMN": "Temperature of Equilibration [degC]",
      "PRESEQREL": "Equilibrator Pressure (relative) [hPa]",
      "PRESEQABS": "Equilibrator Pressure (absolute) [hPa]",
      "WMXRZZ01": "H2O Mole Fraction [umol mol-1]",
      "PRESEQ": "Pressure in Equilibrator [hPa]",
      "DELTAT": "Water-Equilibrator Temperature Difference [°C]",
      "MWMXRCORR": "Marine True Moisture [umol mol-1]",
      "RH2OX0EQ": "Water Vapour Pressure [hPa]",
      "CPVPZZ01": "Atmosphere Water Vapour Pressure [hPa]",
      "XCO2WBDY": "xCO2 In Water - Dry Air [umol mol-1]",
      "XCO2DCEQ": "xCO2 In Water - Calibrated In Dry Air [umol mol-1]",
      "PCO2IG02": "pCO2 In Water - Equilibrator Temperature [uatm]",
      "FCO2IG02": "fCO2 In Water - Equilibrator Temperature [uatm]",
      "AWMXRCORR": "Atmosphere True Moisture [umol mol-1]",
      "CAPAZZ01": "Atmospheric Pressure At Sea Level [hPa]",
      "XCO2DRAT": "xCO2 In Atmoshpere - Dry Air [mol mol-1]",
      "XCO2DCMA": "xCO2 In Atmosphere - Calibrated In Dry Air [mol mol-1]",
      "LPRES0EQ_equil": "LICOR Pressure (Equilibrator) [hPa]",
      "LPRES0EQ_atm": "LICOR Pressure (Atmosphere) [hPa]",
      "CTMPZZ01": "Atmospheric Temperature [degC]"
    }
  },
  {
    "exportName": "ICOS OTC No Salinity Flags",
    "separator": "comma",
    "includeCalculationColumns": true,
    "exportDataClass": "NeutraliseSalinityFlagsExportData",
    "visible": false,
    "timestampHeader": "Date/Time",
    "replaceColumnHeaders": {
      "ALATGP01": "Latitude",
      "ALONGP01": "Longitude",
      "PSALPR01": "P_sal [psu]",
      "TEMPPR01": "Temp [degC]",
      "FCO2XXXX": "fCO2 [uatm]",
      "PCO2TK02": "pCO2 [uatm]",
      "ACO2XXXX": "pCO2 in atmosphere [uatm]",
      "FCO2WTAT": "fCO2 in atmosphere [uatm]",
      "ADEPZZ01": "Depth [m]",
      "CAPHZZ01": "Atmospheric Pressure [hPa]",
      "PRESAMB": "Instrument Ambient Pressure [hPa]",
      "XCO2EQWT": "CO2 Mole Fraction [umol mol-1]",
      "TEMPEQMN": "Temperature of Equilibration [degC]",
      "PRESEQREL": "Equilibrator Pressure (relative) [hPa]",
      "PRESEQABS": "Equilibrator Pressure (absolute) [hPa]",
      "WMXRZZ01": "H2O Mole Fraction [umol mol-1]",
      "PRESEQ": "Pressure in Equilibrator [hPa]",
      "DELTAT": "Water-Equilibrator Temperature Difference [°C]",
      "MWMXRCORR": "Marine True Moisture [umol mol-1]",
      "RH2OX0EQ": "Water Vapour Pressure [hPa]",
      "CPVPZZ01": "Atmosphere Water Vapour Pressure [hPa]",
      "XCO2WBDY": "xCO2 In Water - Dry Air [umol mol-1]",
      "XCO2DECQ": "xCO2 In Water - Calibrated In Dry Air [umol mol-1]",
      "PCO2IG02": "pCO2 In Water - Equilibrator Temperature [uatm]",
      "FCO2IG02": "fCO2 In Water - Equilibrator Temperature [uatm]",
      "AWMXRCORR": "Atmosphere True Moisture [umol mol-1]",
      "CAPAZZ01": "Atmospheric Pressure At Sea Level [hPa]",
      "XCO2DRAT": "xCO2 In Atmoshpere - Dry Air [mol mol-1]",
      "XCO2DCMA": "xCO2 In Atmosphere - Calibrated In Dry Air [mol mol-1]",
      "LPRES0EQ_equil": "LICOR Pressure (Equilibrator) [hPa]",
      "LPRES0EQ_atm": "LICOR Pressure (Atmosphere) [hPa]",
      "CTMPZZ01": "Atmospheric Temperature [degC]"
    }
  },
  {
    "exportName": "ICOS OTC Labelling",
    "separator": "comma",
    "includeCalculationColumns": true,
    "includeRawSensors": true,
    "includeUnits": false,
    "visible": false,
    "timestampHeader": "Date/Time",
    "replaceColumnHeaders": {
      "ALATGP01": "Latitude",
      "ALONGP01": "Longitude",
      "PSALPR01": "P_sal [psu]",
      "TEMPPR01": "Temp [degC]",
      "FCO2XXXX": "fCO2 [uatm]",
      "PCO2TK02": "pCO2 [uatm]",
      "ACO2XXXX": "pCO2 in atmosphere [uatm]",
      "FCO2WTAT": "fCO2 in atmosphere [uatm]",
      "ADEPZZ01": "Depth [m]",
      "CAPHZZ01": "Atmospheric Pressure [hPa]",
      "PRESAMB": "Instrument Ambient Pressure [hPa]",
      "XCO2EQWT": "CO2 Mole Fraction [umol mol-1]",
      "TEMPEQMN": "Temperature of Equilibration [degC]",
      "PRESEQREL": "Equilibrator Pressure (relative) [hPa]",
      "PRESEQABS": "Equilibrator Pressure (absolute) [hPa]",
      "WMXRZZ01": "H2O Mole Fraction [umol mol-1]",
      "PRESEQ": "Pressure in Equilibrator [hPa]",
      "DELTAT": "Water-Equilibrator Temperature Difference [°C]",
      "MWMXRCORR": "Marine True Moisture [umol mol-1]",
      "RH2OX0EQ": "Water Vapour Pressure [hPa]",
      "CPVPZZ01": "Atmosphere Water Vapour Pressure [hPa]",
      "XCO2WBDY": "xCO2 In Water - Dry Air [umol mol-1]",
      "XCO2DECQ": "xCO2 In Water - Calibrated In Dry Air [umol mol-1]",
      "PCO2IG02": "pCO2 In Water - Equilibrator Temperature [uatm]",
      "FCO2IG02": "fCO2 In Water - Equilibrator Temperature [uatm]",
      "AWMXRCORR": "Atmosphere True Moisture [umol mol-1]",
      "CAPAZZ01": "Atmospheric Pressure At Sea Level [hPa]",
      "XCO2DRAT": "xCO2 In Atmoshpere - Dry Air [mol mol-1]",
      "XCO2DCMA": "xCO2 In Atmosphere - Calibrated In Dry Air [mol mol-1]",
      "LPRES0EQ_equil": "LICOR Pressure (Equilibrator) [hPa]",
      "LPRES0EQ_atm": "LICOR Pressure (Atmosphere) [hPa]",
      "CTMPZZ01": "Atmospheric Temperature [degC]"
    }
  },
  {
    "exportName": "Copernicus",
    "separator": "comma",
    "variables": ["Underway Marine pCO₂","SailDrone Marine CO₂ NRT"],
    "includeCalculationColumns": false,
    "useColumnCodes": true,
    "includeUnits": false,
    "includeQCComments": false,
    "qcFlagSuffix": "_QC",
    "timestampHeader": "Timestamp",
    "headerMode": "code"
  },
  {
    "exportName": "Copernicus No Salinity Flags",
    "separator": "comma",
    "variables": ["Underway Marine pCO₂"],
    "includeCalculationColumns": false,
    "useColumnCodes": true,
    "includeUnits": false,
    "includeQCComments": false,
    "qcFlagSuffix": "_QC",
    "timestampHeader": "Timestamp",
    "headerMode": "code",
    "exportDataClass": "NeutraliseSalinityFlagsExportData",
    "visible": false
  }
]
